description2process/__init__.py
description2process/activity_extraction.py
description2process/activity_recognition.py
description2process/activity_recognition_old.py
description2process/activity_recognition_old2.py
description2process/clause_extraction.py
description2process/contraction_expansion.py
description2process/coreference_resolution.py
description2process/data_generation.py
description2process/evaluation.py
description2process/structured_description.py
description2process/visualization.py
description2process/xml_model.py
description2process/data/data_generation_content.xlsx
description2process-0.1.1.dist-info/LICENSE
description2process-0.1.1.dist-info/METADATA
description2process-0.1.1.dist-info/WHEEL
description2process-0.1.1.dist-info/top_level.txt
description2process-0.1.1.dist-info/RECORD
