Metadata-Version: 2.1
Name: description2process
Version: 0.1.1
Summary: Library for constructing a process model given the process description. Deep learning techniques are implmented as much as possible.
Home-page: https://github.com/pypa/sampleproject
Author: Simeon & Niels
Author-email: author@example.com
License: UNKNOWN
Platform: UNKNOWN
Classifier: Programming Language :: Python :: 3
Classifier: License :: OSI Approved :: MIT License
Classifier: Operating System :: OS Independent
Requires-Dist: neuralcoref
Requires-Dist: benepar
Requires-Dist: allennlp
Requires-Dist: graphviz
Requires-Dist: spacy
Requires-Dist: tensorflow
Requires-Dist: tensor2tensor
